deltax/__init__.py
deltax/robot.py
deltax-0.0.1.6.dist-info/LICENCE.txt
deltax-0.0.1.6.dist-info/METADATA
deltax-0.0.1.6.dist-info/WHEEL
deltax-0.0.1.6.dist-info/top_level.txt
deltax-0.0.1.6.dist-info/RECORD
