Metadata-Version: 2.1
Name: deltax
Version: 0.0.1.6
Summary: Python library to control an DeltaX robot
Home-page: https://github.com/VanThanBK/python-deltax
Author: Than Nguyen
Author-email: jonyvanthan@gmail.com
License: UNKNOWN
Project-URL: Bug Tracker, https://github.com/VanThanBK/python-deltax
Platform: UNKNOWN
Classifier: Programming Language :: Python :: 3
Classifier: License :: OSI Approved :: MIT License
Classifier: Operating System :: OS Independent
Requires-Python: >=3.6
License-File: LICENCE.txt
